{
      "RELATIONS": [
            {
                  "idTable": 0,
                  "TableName": "labs",
                  "ColumnsNo": 3,
                  "FragmentationType": "H",
                  "FragCount": 4
            },
            {
                  "idTable": 1,
                  "TableName": "faculty",
                  "ColumnsNo": 4,
                  "FragmentationType": "DH",
                  "FragCount": 4
            },
            {
                  "idTable": 2,
                  "TableName": "students",
                  "ColumnsNo": 7,
                  "FragmentationType": "V",
                  "FragCount": 3
            }
      ],
      "FRAGMENTATION": [
            {
                  "FragmentationID": 0,
                  "FragmentationCondition": "labs.lab_location==KCIS",
                  "SiteId": "1",
                  "RelationId": 0
            },
            {
                  "FragmentationID": 1,
                  "FragmentationCondition": "labs.lab_location==VINDHYA",
                  "SiteId": "2",
                  "RelationId": 0
            },
            {
                  "FragmentationID": 2,
                  "FragmentationCondition": "labs.lab_location==HIMALAYA",
                  "SiteId": "3",
                  "RelationId": 0
            },
            {
                  "FragmentationID": 3,
                  "FragmentationCondition": "labs.lab_location==NILGIRI",
                  "SiteId": "4",
                  "RelationId": 0
            },
            {
                  "FragmentationID": 4,
                  "FragmentationCondition": "labId,lab_id,labs.lab_location==KCIS",
                  "SiteId": "1",
                  "RelationId": 1
            },
            {
                  "FragmentationID": 5,
                  "FragmentationCondition": "labId,lab_id,labs.lab_location==VINDHYA",
                  "SiteId": "2",
                  "RelationId": 1
            },
            {
                  "FragmentationID": 6,
                  "FragmentationCondition": "labId,lab_id,labs.lab_location==HIMALAYA",
                  "SiteId": "3",
                  "RelationId": 1
            },
            {
                  "FragmentationID": 7,
                  "FragmentationCondition": "labId,lab_id,labs.lab_location==NILGIRI",
                  "SiteId": "4",
                  "RelationId": 1
            },
            {
                  "FragmentationID": 8,
                  "FragmentationCondition": "7,8,9",
                  "SiteId": "1",
                  "RelationId": 2
            },
            {
                  "FragmentationID": 9,
                  "FragmentationCondition": "7,10,11",
                  "SiteId": "2",
                  "RelationId": 2
            },
            {
                  "FragmentationID": 10,
                  "FragmentationCondition": "7,12,13",
                  "SiteId": "3",
                  "RelationId": 2
            }
      ],
      "COLUMNS": [
            {
                  "ColumnID": 0,
                  "ColumnType": "Varchar (50)",
                  "ColumnName": "lab_id",
                  "TableID": 0
            },
            {
                  "ColumnID": 1,
                  "ColumnType": "Varchar (50)",
                  "ColumnName": "lab_name",
                  "TableID": 0
            },
            {
                  "ColumnID": 2,
                  "ColumnType": "Varchar (50)",
                  "ColumnName": "lab_location",
                  "TableID": 0
            },
            {
                  "ColumnID": 3,
                  "ColumnType": "Varchar (50)",
                  "ColumnName": "faculty_id",
                  "TableID": 1
            },
            {
                  "ColumnID": 4,
                  "ColumnType": "Varchar (50)",
                  "ColumnName": "fname",
                  "TableID": 1
            },
            {
                  "ColumnID": 5,
                  "ColumnType": "Varchar (50)",
                  "ColumnName": "lname",
                  "TableID": 1
            },
            {
                  "ColumnID": 6,
                  "ColumnType": "Varchar (50)",
                  "ColumnName": "labId",
                  "TableID": 1
            },
            {
                  "ColumnID": 7,
                  "ColumnType": "Varchar (50)",
                  "ColumnName": "rno",
                  "TableID": 2
            },
            {
                  "ColumnID": 8,
                  "ColumnType": "Varchar (50)",
                  "ColumnName": "fname",
                  "TableID": 2
            },
            {
                  "ColumnID": 9,
                  "ColumnType": "Varchar (50)",
                  "ColumnName": "lname",
                  "TableID": 2
            },
            {
                  "ColumnID": 10,
                  "ColumnType": "Varchar (50)",
                  "ColumnName": "cgpa",
                  "TableID": 2
            },
            {
                  "ColumnID": 11,
                  "ColumnType": "Varchar (50)",
                  "ColumnName": "expense",
                  "TableID": 2
            },
            {
                  "ColumnID": 12,
                  "ColumnType": "Varchar (50)",
                  "ColumnName": "branch",
                  "TableID": 2
            },
            {
                  "ColumnID": 13,
                  "ColumnType": "Varchar (50)",
                  "ColumnName": "facId",
                  "TableID": 2
            }
      ],
      "SITES": [
            {
                  "idSite": 1,
                  "User": "user",
                  "ip": "10.3.5.211",
                  "password": "iiit123",
                  "HostName": "CP5"
            },
            {
                  "idSite": 2,
                  "User": "user",
                  "ip": "10.3.5.208",
                  "password": "iiit123",
                  "HostName": "CP6"
            },
            {
                  "idSite": 3,
                  "User": "user",
                  "ip": "10.3.5.204",
                  "password": "iiit123",
                  "HostName": "CP7"
            },
            {
                  "idSite": 4,
                  "User": "user",
                  "ip": "10.3.5.205",
                  "password": "iiit123",
                  "HostName": "CP8"
            }
      ]
}